kenobi_hello/__init__.py
kenobi_hello/__main__.py
kenobi_hello-1.0.1.dist-info/LICENSE
kenobi_hello-1.0.1.dist-info/METADATA
kenobi_hello-1.0.1.dist-info/WHEEL
kenobi_hello-1.0.1.dist-info/entry_points.txt
kenobi_hello-1.0.1.dist-info/top_level.txt
kenobi_hello-1.0.1.dist-info/RECORD
