Metadata-Version: 2.1
Name: kenobi-hello
Version: 1.0.1
Summary: Kenobi's Hello World
Home-page: UNKNOWN
Author: Guilherme Cartier
Author-email: gcartier94@gmail.com
License: UNKNOWN
Platform: UNKNOWN
Classifier: License :: OSI Approved :: Apache Software License
Classifier: Programming Language :: Python :: 3
Classifier: Programming Language :: Python :: 3.7
Classifier: Programming Language :: Python :: 3.8
